langchain_prefect/__init__.py
langchain_prefect/_version.py
langchain_prefect/loaders.py
langchain_prefect/plugins.py
langchain_prefect/types.py
langchain_prefect/utilities.py
langchain_prefect-0.0.3.dist-info/LICENSE
langchain_prefect-0.0.3.dist-info/METADATA
langchain_prefect-0.0.3.dist-info/WHEEL
langchain_prefect-0.0.3.dist-info/entry_points.txt
langchain_prefect-0.0.3.dist-info/top_level.txt
langchain_prefect-0.0.3.dist-info/RECORD
