Metadata-Version: 2.1
Name: langchain-prefect
Version: 0.0.3
Summary: Orchestrate and observe tools built with langchain.
Home-page: https://github.com/PrefectHQ/langchain-prefect
Author: Prefect Technologies
Author-email: nate@prefect.io
License: Apache License 2.0
Keywords: prefect
Classifier: Natural Language :: English
Classifier: Intended Audience :: Developers
Classifier: Intended Audience :: System Administrators
Classifier: License :: OSI Approved :: Apache Software License
Classifier: Programming Language :: Python :: 3 :: Only
Classifier: Programming Language :: Python :: 3.10
Classifier: Topic :: Software Development :: Libraries
Requires-Python: >=3.10
License-File: LICENSE
Requires-Dist: prefect (>=2.8.4)
Requires-Dist: langchain (>=0.0.27)
Requires-Dist: tiktoken (>=0.3.0)
Provides-Extra: dev
Requires-Dist: pytest ; extra == 'dev'
Requires-Dist: black ; extra == 'dev'
Requires-Dist: mypy ; extra == 'dev'
Requires-Dist: mkdocs ; extra == 'dev'
Requires-Dist: mkdocs-material ; extra == 'dev'
Requires-Dist: mkdocstrings[python] ; extra == 'dev'
Requires-Dist: pre-commit ; extra == 'dev'
Requires-Dist: pytest-asyncio ; extra == 'dev'
Requires-Dist: mkdocs-gen-files ; extra == 'dev'
Requires-Dist: interrogate ; extra == 'dev'
Requires-Dist: coverage ; extra == 'dev'
Requires-Dist: pillow ; extra == 'dev'
Requires-Dist: openai ; extra == 'dev'
Requires-Dist: ruff ; extra == 'dev'
Requires-Dist: mock ; (python_version < "3.8") and extra == 'dev'
